journey2md/__init__.py
journey2md/__main__.py
journey2md-1.0.0.dist-info/METADATA
journey2md-1.0.0.dist-info/WHEEL
journey2md-1.0.0.dist-info/entry_points.txt
journey2md-1.0.0.dist-info/licenses/LICENSE
journey2md-1.0.0.dist-info/RECORD
